xy_conda/Conda.py
xy_conda/Runner.py
xy_conda/__init__.py
xy_conda/execute/Main.py
xy_conda/execute/__init__.py
xy_conda-1.0.5.dist-info/LICENSE
xy_conda-1.0.5.dist-info/METADATA
xy_conda-1.0.5.dist-info/WHEEL
xy_conda-1.0.5.dist-info/entry_points.txt
xy_conda-1.0.5.dist-info/top_level.txt
xy_conda-1.0.5.dist-info/RECORD
