Metadata-Version: 2.1
Name: xy_conda
Version: 1.0.5
Summary: xy_conda 模块
Author-email: 余洋 <yuyangit.0515@qq.com>
Classifier: Programming Language :: Python :: 3.8
Requires-Python: >=3.8
License-File: LICENSE
Requires-Dist: xy-console
Requires-Dist: xy-argparse
